provenancetoolbox/__init__.py
provenancetoolbox/notebook.py
provenancetoolbox/process.py
provenancetoolbox/utils.py
provenance_toolbox-0.1.5.dist-info/LICENSE
provenance_toolbox-0.1.5.dist-info/METADATA
provenance_toolbox-0.1.5.dist-info/WHEEL
provenance_toolbox-0.1.5.dist-info/top_level.txt
provenance_toolbox-0.1.5.dist-info/RECORD
