Metadata-Version: 2.1
Name: provenance-toolbox
Version: 0.1.5
Summary: Some basic utilities to standardize the use of CloudVolume provenance files
Home-page: https://github.com/ZettaAI/provenance-toolbox
Author: Nicholas Turner
Author-email: nturner@zetta.ai
License: UNKNOWN
Platform: UNKNOWN
License-File: LICENSE
Requires-Dist: GitPython (>=3.1.26)
Requires-Dist: docker (>=5.0.3)
Requires-Dist: cloud-volume
